{
  "development": {
    "dialect": "postgres",
    "username" : "postgres",
    "password" : "postgres",
    "database" : "yukchat",
    "host" : "db",
    "port" : "5432",
    "logging" : false
  },
  "production": {
    "dialect": "postgres",
    "username" : "postgres",
    "password" : "postgres",
    "database" : "yukchat",
    "host" : "db",
    "port" : "5432",
    "logging" : false
  },
  "test": {
    "dialect": "postgres",
    "username" : "postgres",
    "password" : "postgres",
    "database" : "yukchat",
    "host" : "db",
    "port" : "5432",
    "logging" : false
  }
}
